keypad_fsm.srcs/sources_1/new/keypad_fsm.v
`timescale 1ns / 1ps

module keypad_fsm(
    input clk, 
    input reset,
    input [3:0] key_in,
    input key_valid,
    output reg unlocked,
    output [1:0] state  // state is now a wire assigned from current_state
);

// FSM states
parameter IDLE = 2'b00, INPUT = 2'b01, CHECK = 2'b10, UNLOCKED = 2'b11;

// Registers for state machine and password handling
reg [1:0] current_state, next_state;
reg [3:0] password[3:0]; 
reg [3:0] input_code[3:0]; 
reg [1:0] count; 
reg match;

// Assign current_state to output state for waveform visibility
assign state = current_state;

// Match logic
always @(*) begin
    match = (input_code[0] == password[0]) &&
            (input_code[1] == password[1]) &&
            (input_code[2] == password[2]) &&
            (input_code[3] == password[3]);
end

// State transition
always @(posedge clk or posedge reset) begin
    if (reset)
        current_state <= IDLE;
    else
        current_state <= next_state;
end

// Next state logic
always @(*) begin
    case (current_state)
        IDLE: next_state = (key_valid) ? INPUT : IDLE;
        INPUT: next_state = (count == 2'd3 && key_valid) ? CHECK : INPUT;
        CHECK: next_state = (match) ? UNLOCKED : IDLE;
        UNLOCKED: next_state = UNLOCKED; // Remain unlocked
        default: next_state = IDLE;
    endcase
end

// Output logic
always @(posedge clk or posedge reset) begin
    if (reset) begin
        unlocked <= 0;
        count <= 0;

        // Set password 1,2,3,4
        password[0] <= 4'd1;
        password[1] <= 4'd2;
        password[2] <= 4'd3;
        password[3] <= 4'd4;
    end else begin
        case (current_state)
            IDLE: begin
                unlocked <= 0;
                count <= 0;
            end
            INPUT: begin
                if (key_valid && count < 4) begin
                    input_code[count] <= key_in;
                    count <= count + 1;
                end
            end
            CHECK: begin
                // nothing needed here; match evaluated in combinational logic
            end
            UNLOCKED: begin
                unlocked <= 1;
            end
        endcase
    end
end

endmodule

keypad_fsm.srcs/sim_1/new/testbench_fsm.v
`timescale 1ns / 1ps

module testbench;

    reg clk, reset, key_valid;
    reg [3:0] key_in;
    wire unlocked;
    wire [1:0] state;

    // Instantiate the FSM
    keypad_fsm uut (
        .clk(clk),
        .reset(reset),
        .key_in(key_in),
        .key_valid(key_valid),
        .unlocked(unlocked),
        .state(state)
    );

    // Clock generation
    initial begin
        clk = 0;
        forever #5 clk = ~clk;
    end

    // Test sequence
    initial begin
        $display("Simulation started...");
        $dumpfile("fsm.vcd");
        $dumpvars(0, testbench);

        reset = 1;
        key_valid = 0;
        key_in = 0;

        #10 reset = 0;

        // Input correct password: 1, 2, 3, 4
        send_key(4'd1);
        send_key(4'd2);
        send_key(4'd3);
        send_key(4'd4);

        #20; // Let FSM update

        if (unlocked)
            $display("✅ Password Correct: UNLOCKED!");
        else
            $display("❌ Password Incorrect: LOCKED!");

        #20;
        $finish;
    end

    // Key sending task
    task send_key(input [3:0] key);
        begin
            key_in = key;
            key_valid = 1;
            #10;
            key_valid = 0;
            #10;
        end
    endtask

endmodule

keypad_fsm.sim/sim_1/behav/xsim/fsm.vcd
$date
   Sun Apr 13 16:51:06 2025
$end

$version
  2024.2.0
  $dumpfile ("fsm.vcd") 
$end

$timescale
  1ps
$end

$scope module testbench $end
$var reg 1 ! clk $end
$var reg 1 " reset $end
$var reg 1 # key_valid $end
$var reg 4 $ key_in [3:0] $end
$var wire 1 % unlocked $end
$var wire 2 & state [1:0] $end
$scope module uut $end
$var wire 1 ' clk $end
$var wire 1 ( reset $end
$var wire 4 ) key_in [3:0] $end
$var wire 1 * key_valid $end
$var reg 1 + unlocked $end
$var wire 2 & state [1:0] $end
$var reg 2 , current_state [1:0] $end
$var reg 2 - next_state [1:0] $end
$var reg 2 . count [1:0] $end
$var reg 1 / match $end
$upscope $end
$scope task send_key $end
$var reg 4 0 key [3:0] $end
$upscope $end
$upscope $end
$enddefinitions $end

#0
$dumpvars
0!
1"
0#
b0 $
0%
b0 &
0'
1(
b0 )
0*
0+
b0 ,
b0 -
b0 .
0/
bx 0
$end

#5000
1!
1'

#10000
0!
0"
1#
b1 $
0'
0(
b1 )
1*
b1 -
b1 0

#15000
1!
b1 &
1'
b1 ,

#20000
0!
0#
0'
0*

#25000
1!
1'

#30000
0!
1#
b10 $
0'
b10 )
1*
b10 0

#35000
1!
1'
b1 .

#40000
0!
0#
0'
0*

#45000
1!
1'

#50000
0!
1#
b11 $
0'
b11 )
1*
b11 0

#55000
1!
1'
b10 .

#60000
0!
0#
0'
0*

#65000
1!
1'

#70000
0!
1#
b100 $
0'
b100 )
1*
b100 0

#75000
1!
1'
b11 .

#80000
0!
0#
0'
0*

