keypad_fsm.srcs/sources_1/new/keypad_fsm.v
`timescale 1ns / 1ps

module keypad_fsm(
    input clk, 
    input reset,
    input [3:0] key_in,
    input key_valid,
    output reg unlocked,
    output [1:0] state  // state is now a wire assigned from current_state
);

// FSM states
parameter IDLE = 2'b00, INPUT = 2'b01, CHECK = 2'b10, UNLOCKED = 2'b11;

// Registers for state machine and password handling
reg [1:0] current_state, next_state;
reg [3:0] password[3:0]; 
reg [3:0] input_code[3:0]; 
reg [1:0] count; 
reg match;

// Assign current_state to output state for waveform visibility
assign state = current_state;

// Match logic
always @(*) begin
    match = (input_code[0] == password[0]) &&
            (input_code[1] == password[1]) &&
            (input_code[2] == password[2]) &&
            (input_code[3] == password[3]);
end

// State transition
always @(posedge clk or posedge reset) begin
    if (reset)
        current_state <= IDLE;
    else
        current_state <= next_state;
end

// Next state logic
always @(*) begin
    case (current_state)
        IDLE: next_state = (key_valid) ? INPUT : IDLE;
        INPUT: next_state = (count == 2'd3 && key_valid) ? CHECK : INPUT;
        CHECK: next_state = (match) ? UNLOCKED : IDLE;
        UNLOCKED: next_state = UNLOCKED; // Remain unlocked
        default: next_state = IDLE;
    endcase
end

// Output logic
always @(posedge clk or posedge reset) begin
    if (reset) begin
        unlocked <= 0;
        count <= 0;

        // Set password 1,2,3,4
        password[0] <= 4'd1;
        password[1] <= 4'd2;
        password[2] <= 4'd3;
        password[3] <= 4'd4;
    end else begin
        case (current_state)
            IDLE: begin
                unlocked <= 0;
                count <= 0;
            end
            INPUT: begin
                if (key_valid && count < 4) begin
                    input_code[count] <= key_in;
                    count <= count + 1;
                end
            end
            CHECK: begin
                // nothing needed here; match evaluated in combinational logic
            end
            UNLOCKED: begin
                unlocked <= 1;
            end
        endcase
    end
end

endmodule

keypad_fsm.srcs/sim_1/new/testbench_fsm.v
`timescale 1ns / 1ps

module testbench;

    reg clk, reset, key_valid;
    reg [3:0] key_in;
    wire unlocked;
    wire [1:0] state;

    // Instantiate the FSM
    keypad_fsm uut (
        .clk(clk),
        .reset(reset),
        .key_in(key_in),
        .key_valid(key_valid),
        .unlocked(unlocked),
        .state(state)
    );

    // Clock generation
    initial begin
        clk = 0;
        forever #5 clk = ~clk;
    end

    // Test sequence
    initial begin
        $display("Simulation started...");
        $dumpfile("fsm.vcd");
        $dumpvars(0, testbench);

        reset = 1;
        key_valid = 0;
        key_in = 0;

        #10 reset = 0;

        // Input correct password: 1, 2, 3, 4
        send_key(4'd1);
        send_key(4'd2);
        send_key(4'd3);
        send_key(4'd4);

        #20; // Let FSM update

        if (unlocked)
            $display("✅ Password Correct: UNLOCKED!");
        else
            $display("❌ Password Incorrect: LOCKED!");

        #20;
        $finish;
    end

    // Key sending task
    task send_key(input [3:0] key);
        begin
            key_in = key;
            key_valid = 1;
            #10;
            key_valid = 0;
            #10;
        end
    endtask

endmodule

keypad_fsm.sim/sim_1/behav/xsim/keypad_fsm_tb.vcd
$date
   Sun Apr 13 16:45:34 2025
$end

$version
  2024.2.0
  $dumpfile ("keypad_fsm_tb.vcd") 
$end

$timescale
  1ps
$end

$scope module testbench $end
$var reg 1 ! clk $end
$var reg 1 " reset $end
$var reg 1 # key_valid $end
$var reg 4 $ key_in [3:0] $end
$var wire 1 % unlocked $end
$var wire 2 & state [1:0] $end
$scope module uut $end
$var wire 1 ' clk $end
$var wire 1 ( reset $end
$var wire 4 ) key_in [3:0] $end
$var wire 1 * key_valid $end
$var reg 1 + unlocked $end
$var wire 2 & state [1:0] $end
$var reg 2 , current_state [1:0] $end
$var reg 2 - next_state [1:0] $end
$var reg 2 . count [1:0] $end
$var reg 1 / match $end
$upscope $end
$scope task send_key $end
$var reg 4 0 key [3:0] $end
$upscope $end
$upscope $end
$enddefinitions $end

#0
$dumpvars
0!
1"
0#
bx $
0%
b0 &
0'
1(
bx )
0*
0+
b0 ,
b0 -
b0 .
0/
bx 0
$end

#5000
1!
1'

#10000
0!
0'

#15000
1!
1'

#20000
0!
0"
0'
0(

#25000
1!
1'

#30000
0!
0'
b1 0

#35000
1!
1'

#36000
1#
b1 $
b1 )
1*
b1 -

#40000
0!
0'

#45000
1!
b1 &
1'
b1 ,

#46000
0#
bx $
bx )
0*
b10 0

#50000
0!
0'

#55000
1!
1'

#56000
1#
b10 $
b10 )
1*

#60000
0!
0'

#65000
1!
1'
b1 .

#66000
0#
bx $
bx )
0*
b11 0

#70000
0!
0'

#75000
1!
1'

#76000
1#
b11 $
b11 )
1*

#80000
0!
0'

#85000
1!
1'
b10 .

#86000
0#
bx $
bx )
0*
b100 0

#90000
0!
0'

#95000
1!
1'

#96000
1#
b100 $
b100 )
1*

#100000
0!
0'

#105000
1!
1'
b11 .

#106000
0#
bx $
bx )
0*

#110000
0!
0'

#115000
1!
1'

#120000
0!
0'

#125000
1!
1'

#130000
0!
0'

#135000
1!
1'

#140000
0!
0'

#145000
1!
1'

#150000
0!
0'

#155000
1!
1'

#156000
1"
b0 &
1(
b0 ,
b0 -
b0 .

#160000
0!
0'

#165000
1!
1'

#170000
0!
0'

#175000
1!
1'

#176000
0"
0(

#180000
0!
0'

#185000
1!
1'

#190000
0!
0'

#195000
1!
1'

#200000
0!
0'

#205000
1!
1'

#206000
b1 0

#210000
0!
0'

#215000
1!
1'

#216000
1#
b1 $
b1 )
1*
b1 -

#220000
0!
0'

#225000
1!
b1 &
1'
b1 ,

#226000
0#
bx $
bx )
0*
b10 0

#230000
0!
0'

#235000
1!
1'

#236000
1#
b10 $
b10 )
1*

#240000
0!
0'

#245000
1!
1'
b1 .

#246000
0#
bx $
bx )
0*
b11 0

#250000
0!
0'

#255000
1!
1'

#256000
1#
b11 $
b11 )
1*

#260000
0!
0'

#265000
1!
1'
b10 .

#266000
0#
bx $
bx )
0*
b101 0

#270000
0!
0'

#275000
1!
1'

#276000
1#
b101 $
b101 )
1*

#280000
0!
0'

#285000
1!
1'
b11 .

#286000
0#
bx $
bx )
0*

#290000
0!
0'

#295000
1!
1'

#300000
0!
0'

#305000
1!
1'

#310000
0!
0'

#315000
1!
1'

#320000
0!
0'

#325000
1!
1'

#330000
0!
0'

#335000
1!
1'

#336000
b1 0

#340000
0!
0'

#345000
1!
1'

#346000
1#
b1 $
b1 )
1*

#350000
0!
0'

#355000
1!
1'
b0 .

#356000
0#
bx $
bx )
0*
b10 0

#360000
0!
0'

#365000
1!
1'

#366000
1#
b10 $
b10 )
1*

#370000
0!
0'

#375000
1!
1'
b1 .

#376000
0#
bx $
bx )
0*

